stt_poetry_package/__init__.py
stt_poetry_package-0.1.0.dist-info/METADATA
stt_poetry_package-0.1.0.dist-info/WHEEL
stt_poetry_package-0.1.0.dist-info/RECORD
