Metadata-Version: 2.3
Name: stt-poetry-package
Version: 0.1.0
Summary: 
Author: jcggl
Author-email: jc@goodganglabs.com
Requires-Python: >3.9.1,<4.0
Classifier: Programming Language :: Python :: 3
Classifier: Programming Language :: Python :: 3.10
Classifier: Programming Language :: Python :: 3.11
Classifier: Programming Language :: Python :: 3.12
Classifier: Programming Language :: Python :: 3.13
Requires-Dist: absl-py (>=2.2.2,<3.0.0)
Requires-Dist: accelerate (>=1.6.0,<2.0.0)
Requires-Dist: aiohappyeyeballs (>=2.6.1,<3.0.0)
Requires-Dist: aiohttp (>=3.11.17,<4.0.0)
Requires-Dist: aiosignal (>=1.3.2,<2.0.0)
Requires-Dist: anyio (>=4.9.0,<5.0.0)
Requires-Dist: async-timeout (>=5.0.1,<6.0.0)
Requires-Dist: attrs (>=25.3.0,<26.0.0)
Requires-Dist: audioread (>=3.0.1,<4.0.0)
Requires-Dist: backports-tarfile (>=1.2.0,<2.0.0)
Requires-Dist: bitsandbytes (>=0.45.5,<0.46.0)
Requires-Dist: build (>=1.2.2.post1,<2.0.0)
Requires-Dist: cachecontrol (>=0.14.3,<0.15.0)
Requires-Dist: certifi (>=2025.1.31,<2026.0.0)
Requires-Dist: cffi (>=1.17.1,<2.0.0)
Requires-Dist: charset-normalizer (>=3.4.1,<4.0.0)
Requires-Dist: click (>=8.1.8,<9.0.0)
Requires-Dist: crashtest (>=0.4.1,<0.5.0)
Requires-Dist: cryptography (>=44.0.3,<45.0.0)
Requires-Dist: datasets (>=3.0.0,<4.0.0)
Requires-Dist: decorator (>=5.2.1,<6.0.0)
Requires-Dist: dill (>=0.3.8,<0.4.0)
Requires-Dist: distlib (>=0.3.9,<0.4.0)
Requires-Dist: dulwich (>=0.22.8,<0.23.0)
Requires-Dist: evaluate (>=0.4.3,<0.5.0)
Requires-Dist: exceptiongroup (>=1.3.0,<2.0.0)
Requires-Dist: fastjsonschema (>=2.21.1,<3.0.0)
Requires-Dist: filelock (>=3.13.1,<4.0.0)
Requires-Dist: findpython (>=0.6.3,<0.7.0)
Requires-Dist: frozenlist (>=1.6.0,<2.0.0)
Requires-Dist: fsspec (>=2024.6.1,<2025.0.0)
Requires-Dist: grpcio (>=1.71.0,<2.0.0)
Requires-Dist: gtts (>=2.5.4,<3.0.0)
Requires-Dist: h11 (>=0.16.0,<0.17.0)
Requires-Dist: httpcore (>=1.0.9,<2.0.0)
Requires-Dist: httpx (>=0.28.1,<0.29.0)
Requires-Dist: huggingface-hub (>=0.30.2,<0.31.0)
Requires-Dist: idna (>=3.10,<4.0)
Requires-Dist: importlib-metadata (>=8.6.1,<9.0.0)
Requires-Dist: installer (>=0.7.0,<0.8.0)
Requires-Dist: jaraco-classes (>=3.4.0,<4.0.0)
Requires-Dist: jaraco-context (>=6.0.1,<7.0.0)
Requires-Dist: jaraco-functools (>=4.1.0,<5.0.0)
Requires-Dist: jeepney (>=0.9.0,<0.10.0)
Requires-Dist: jinja2 (>=3.1.4,<4.0.0)
Requires-Dist: jiwer (>=3.1.0,<4.0.0)
Requires-Dist: joblib (>=1.4.2,<2.0.0)
Requires-Dist: keyring (>=25.6.0,<26.0.0)
Requires-Dist: lazy-loader (>=0.4,<0.5)
Requires-Dist: librosa (>=0.11.0,<0.12.0)
Requires-Dist: llvmlite (>=0.43.0,<0.44.0)
Requires-Dist: markdown (>=3.8,<4.0)
Requires-Dist: markupsafe (>=2.1.5,<3.0.0)
Requires-Dist: more-itertools (>=10.7.0,<11.0.0)
Requires-Dist: mpmath (>=1.3.0,<2.0.0)
Requires-Dist: msgpack (>=1.1.0,<2.0.0)
Requires-Dist: multidict (>=6.4.3,<7.0.0)
Requires-Dist: multiprocess (>=0.70.16,<0.71.0)
Requires-Dist: networkx (>=3.2.1,<4.0.0)
Requires-Dist: numba (>=0.60.0,<0.61.0)
Requires-Dist: numpy (>=2.0.2,<3.0.0)
Requires-Dist: packaging (>=25.0,<26.0)
Requires-Dist: pandas (>=2.2.3,<3.0.0)
Requires-Dist: pbs-installer (>=2025.4.9,<2026.0.0)
Requires-Dist: peft (>=0.15.2.dev0,<0.16.0)
Requires-Dist: pip (>=25.0,<26.0)
Requires-Dist: pkginfo (>=1.12.1.2,<2.0.0.0)
Requires-Dist: platformdirs (>=4.3.7,<5.0.0)
Requires-Dist: poetry (>=2.1.3,<3.0.0)
Requires-Dist: poetry-core (>=2.1.3,<3.0.0)
Requires-Dist: pooch (>=1.8.2,<2.0.0)
Requires-Dist: propcache (>=0.3.1,<0.4.0)
Requires-Dist: protobuf (>=6.30.2,<7.0.0)
Requires-Dist: psutil (>=7.0.0,<8.0.0)
Requires-Dist: pyarrow (>=19.0.1,<20.0.0)
Requires-Dist: pycparser (>=2.22,<3.0)
Requires-Dist: pyproject-hooks (>=1.2.0,<2.0.0)
Requires-Dist: python-dateutil (>=2.9.0.post0,<3.0.0)
Requires-Dist: python-dotenv (>=1.1.0,<2.0.0)
Requires-Dist: pytz (>=2025.2,<2026.0)
Requires-Dist: pyyaml (>=6.0.2,<7.0.0)
Requires-Dist: rapidfuzz (>=3.13.0,<4.0.0)
Requires-Dist: regex (>=2024.11.6,<2025.0.0)
Requires-Dist: requests (>=2.32.3,<3.0.0)
Requires-Dist: requests-toolbelt (>=1.0.0,<2.0.0)
Requires-Dist: safetensors (>=0.5.3,<0.6.0)
Requires-Dist: scikit-learn (>=1.6.1,<2.0.0)
Requires-Dist: scipy (>=1.13.1,<2.0.0)
Requires-Dist: secretstorage (>=3.3.3,<4.0.0)
Requires-Dist: setuptools (>=75.8.0,<76.0.0)
Requires-Dist: shellingham (>=1.5.4,<2.0.0)
Requires-Dist: six (>=1.17.0,<2.0.0)
Requires-Dist: sniffio (>=1.3.1,<2.0.0)
Requires-Dist: soundfile (>=0.13.1,<0.14.0)
Requires-Dist: soxr (>=0.5.0.post1,<0.6.0)
Requires-Dist: sympy (>=1.13.1,<2.0.0)
Requires-Dist: tensorboard (>=2.19.0,<3.0.0)
Requires-Dist: tensorboard-data-server (>=0.7.2,<0.8.0)
Requires-Dist: threadpoolctl (>=3.6.0,<4.0.0)
Requires-Dist: tokenizers (>=0.20.3,<0.21.0)
Requires-Dist: tomli (>=2.2.1,<3.0.0)
Requires-Dist: tomlkit (>=0.13.2,<0.14.0)
Requires-Dist: torch (==2.3.1)
Requires-Dist: torchaudio (==2.3.1)
Requires-Dist: tqdm (>=4.67.1,<5.0.0)
Requires-Dist: transformers (>=4.46.3,<5.0.0)
Requires-Dist: triton (>=2.3.1,<3.0.0)
Requires-Dist: trove-classifiers (>=2025.5.9.12,<2026.0.0.0)
Requires-Dist: typing-extensions (>=4.12.2,<5.0.0)
Requires-Dist: tzdata (>=2025.2,<2026.0)
Requires-Dist: urllib3 (>=2.4.0,<3.0.0)
Requires-Dist: uv (>=0.7.3,<0.8.0)
Requires-Dist: virtualenv (>=20.31.2,<21.0.0)
Requires-Dist: werkzeug (>=3.1.3,<4.0.0)
Requires-Dist: wheel (>=0.45.1,<0.46.0)
Requires-Dist: xxhash (>=3.5.0,<4.0.0)
Requires-Dist: yarl (>=1.20.0,<2.0.0)
Requires-Dist: zipp (>=3.21.0,<4.0.0)
Requires-Dist: zstandard (>=0.23.0,<0.24.0)
